iniamet/__init__.py
iniamet/__main__.py
iniamet/api_client.py
iniamet/cache.py
iniamet/client.py
iniamet/config.py
iniamet/data.py
iniamet/qc.py
iniamet/regional.py
iniamet/stations.py
iniamet/utils.py
iniamet/visualization.py
iniamet-0.1.1.dist-info/licenses/LICENSE
iniamet-0.1.1.dist-info/METADATA
iniamet-0.1.1.dist-info/WHEEL
iniamet-0.1.1.dist-info/top_level.txt
iniamet-0.1.1.dist-info/RECORD
