Metadata-Version: 2.4
Name: iniamet
Version: 0.1.1
Summary: Unofficial Python library for accessing Chilean INIA agrometeorological station data
Author-email: René Castillo <renecastillo@inia.cl>
Maintainer-email: René Castillo <renecastillo@inia.cl>
License: MIT
Project-URL: Homepage, https://github.com/reneignacio/iniamet-library
Project-URL: Documentation, https://github.com/reneignacio/iniamet-library#readme
Project-URL: Repository, https://github.com/reneignacio/iniamet-library
Project-URL: Bug Tracker, https://github.com/reneignacio/iniamet-library/issues
Project-URL: Changelog, https://github.com/reneignacio/iniamet-library/blob/main/CHANGELOG.md
Project-URL: API Reference, https://agromet.inia.cl/api/v2
Keywords: inia,climate,weather,agrometeorological,chile,api,meteorology,unofficial
Classifier: Development Status :: 4 - Beta
Classifier: Intended Audience :: Science/Research
Classifier: Intended Audience :: Developers
Classifier: License :: OSI Approved :: MIT License
Classifier: Programming Language :: Python :: 3
Classifier: Programming Language :: Python :: 3.8
Classifier: Programming Language :: Python :: 3.9
Classifier: Programming Language :: Python :: 3.10
Classifier: Programming Language :: Python :: 3.11
Classifier: Programming Language :: Python :: 3.12
Classifier: Topic :: Scientific/Engineering :: Atmospheric Science
Classifier: Topic :: Scientific/Engineering :: GIS
Classifier: Operating System :: OS Independent
Requires-Python: >=3.8
License-File: LICENSE
Requires-Dist: requests>=2.28.0
Requires-Dist: pandas>=1.5.0
Requires-Dist: numpy>=1.23.0
Provides-Extra: viz
Requires-Dist: folium>=0.14.0; extra == "viz"
Requires-Dist: ipython>=7.0.0; extra == "viz"
Provides-Extra: dev
Requires-Dist: pytest>=7.0.0; extra == "dev"
Requires-Dist: pytest-cov>=4.0.0; extra == "dev"
Requires-Dist: black>=22.0.0; extra == "dev"
Requires-Dist: flake8>=5.0.0; extra == "dev"
Requires-Dist: mypy>=0.990; extra == "dev"
Provides-Extra: all
Requires-Dist: folium>=0.14.0; extra == "all"
Requires-Dist: ipython>=7.0.0; extra == "all"
Dynamic: license-file
Dynamic: requires-python
